RISC_5_PRO.v
//“Designed a 32-bit 5-stage pipelined RISC-V processor in Verilog supporting R, I, Load/Store, 
//and Branch instructions with control unit, ALU, and memory integration.”
//

//Here we starting our work from the accumiltion of instructions in the instruction memory,based on the models of R,I,B,S.
//we are extracting the data for manupulation,here our most wanted thing is the data which we need to use for computations.
//in R-type it is in the rs1,rs2 address,in I,BS it is immediate type hence we only observing what we need in the code.
//what is useful for our further calculations.

// Supports basic R, I, Load/Store, Branch instructions
// Has 5 pipeline stages (IF, ID, EX, MEM, WB)
// Has control unit + ALU + register file + data memory
// Executes small instruction sequences correctly

module pipeline_riscv(input clk1,clk2);

// ================= IF STAGE =================
reg [31:0] pc; // programe counter for instructions showing
reg [31:0] instr_mem [0:255]; //instruction memeory
reg [31:0] regs [0:31];
reg [31:0] data_mem [0:255];
integer i;  //declarations outside loop for verilog

// 2  initial block and keeep something in memory
initial begin
    
    pc = 0;

    
    for (i = 0; i < 32; i = i + 1)
        regs[i] = 0;

    for (i = 0; i < 256; i = i + 1)
        data_mem[i] = 0;
end

//Fetch instruction using PC(IF stage)
wire [31:0] instruction = instr_mem[pc[9:2]]; //instruction fetching here we are using 256 adress so used pc[9:2]

always @(posedge clk1)
    pc <= pc + 4;//as we using 32 bit word so 8_bit 4 bytes comes in picture thats why next address is at +4

// IF/ID pipeline register
reg [31:0] IF_ID_instr; //to store next stage instructions
always @(posedge clk1)
    IF_ID_instr <= instruction;


// ================= ID STAGE =================

// Instruction fields
wire [6:0] opcode = IF_ID_instr[6:0]; //for R-type
wire [4:0] rs1 = IF_ID_instr[19:15];
wire [4:0] rs2 = IF_ID_instr[24:20];
wire [4:0] rd  = IF_ID_instr[11:7];
wire [2:0] funct3 = IF_ID_instr[14:12];
wire [6:0] funct7 = IF_ID_instr[31:25];

// Immediate generation
wire [31:0] imm_i = {{20{IF_ID_instr[31]}}, IF_ID_instr[31:20]}; //for I-type
wire [31:0] imm_s = {{20{IF_ID_instr[31]}}, IF_ID_instr[31:25], IF_ID_instr[11:7]};//for S-type
wire [31:0] imm_b = {{19{IF_ID_instr[31]}}, IF_ID_instr[31], IF_ID_instr[7],
                     IF_ID_instr[30:25], IF_ID_instr[11:8], 1'b0};// for B-type

// Register file
//reg [31:0] regs [0:31];at first initialized
wire [31:0] reg_data1 = regs[rs1];//outputs of register file
wire [31:0] reg_data2 = regs[rs2];

// Control signals
reg reg_write, alu_src, branch; 
reg mem_write, mem_read, mem_to_reg;
reg [2:0] alu_ctrl;     //reg_write enables writing result to register        //alu_ctrl selects the ALU operation (add, sub)
                        //alu_src selects register vs immediate input to ALU  //branch decides PC jump
                        //mem_write enables writing data into memory (store)
                        //mem_read enables reading data from memory (load).
                        //mem_to_reg enables to give control signal to mux at WB stage
// Control Unit
always @(*) begin
    // default values (VERY IMPORTANT) //intiations for our signals
    reg_write = 0; alu_src = 0; branch = 0;
    mem_write = 0; mem_read = 0; mem_to_reg = 0;
    alu_ctrl  = 3'b000;

    case(opcode)

        // R-TYPE
        7'b0110011: begin
            reg_write = 1; 
            case({funct7, funct3}) //funs are helpful in deciding what operation we are doing and its sub type clearly
                {7'b0000000,3'b000}: alu_ctrl = 3'b000; // ADD
                {7'b0100000,3'b000}: alu_ctrl = 3'b001; // SUB
                {7'b0000000,3'b111}: alu_ctrl = 3'b010; // AND
                {7'b0000000,3'b110}: alu_ctrl = 3'b011; // OR
            endcase
        end

        // I-TYPE
        7'b0010011: begin
            reg_write = 1;
            alu_src   = 1;
            case(funct3)
                3'b000: alu_ctrl = 3'b000; // ADDI
                3'b111: alu_ctrl = 3'b010; // ANDI
                3'b110: alu_ctrl = 3'b011; // ORI
            endcase
        end
                         //reg_write enables writing result to register        //alu_ctrl selects the ALU operation (add, sub)
                        //alu_src selects register vs immediate input to ALU  //branch decides PC jump
                        //mem_write enables writing data into memory (store)
                        //mem_read enables reading data from memory (load).
                        //mem_to_reg enables to give control signal to mux at WB stage
        // LOAD
        7'b0000011: begin
            reg_write = 1;
            alu_src   = 1;
            mem_read  = 1;
            mem_to_reg = 1;
            alu_ctrl  = 3'b000;
        end

        // STORE
        7'b0100011: begin
            alu_src   = 1;
            mem_write = 1;
            alu_ctrl  = 3'b000;
        end

        // BRANCH
        7'b1100011: begin
            branch   = 1;
            alu_ctrl = 3'b001; // SUB (compare)
        end
    endcase
end

// Select immediate
reg [31:0] imm;
always @(*) begin
    case(opcode)
        7'b0010011, 7'b0000011: imm = imm_i;
        7'b0100011: imm = imm_s;
        7'b1100011: imm = imm_b;
        default:    imm = 0;
    endcase
end

// ================= ID/EX =================
reg [31:0] ID_EX_A, ID_EX_B, ID_EX_imm; //storing values of register file for EX stge
reg [4:0]  ID_EX_rd;                    //it runs s it is tilll dat memory alocation
reg [2:0]  ID_EX_alu_ctrl;              //extend of alu_ctrl
reg ID_EX_reg_write, ID_EX_alu_src;
reg ID_EX_mem_write, ID_EX_mem_read, ID_EX_mem_to_reg; // extensions of reg_write = 0; alu_src = 0; branch = 0;
                                                       // mem_write = 0; mem_read = 0; mem_to_reg = 0;
                                                       //alu_ctrl  = 3'b000;

always @(posedge clk2) begin
    ID_EX_A <= reg_data1; //this are registers so values hold after clock cycle
    ID_EX_B <= reg_data2;
    ID_EX_imm <= imm;
    ID_EX_rd <= rd;

    ID_EX_alu_ctrl <= alu_ctrl;
    ID_EX_reg_write <= reg_write;
    ID_EX_alu_src <= alu_src;
    ID_EX_mem_write <= mem_write;
    ID_EX_mem_read <= mem_read;
    ID_EX_mem_to_reg <= mem_to_reg;
end


// ================= EX =================
wire [31:0] alu_in2 = (ID_EX_alu_src) ? ID_EX_imm : ID_EX_B; //// at input B the data may comes from input B or immideate value

reg [31:0] alu_result; //output of alu
always @(*) begin
    case(ID_EX_alu_ctrl)
        3'b000: alu_result = ID_EX_A + alu_in2;
        3'b001: alu_result = ID_EX_A - alu_in2;
        3'b010: alu_result = ID_EX_A & alu_in2;
        3'b011: alu_result = ID_EX_A | alu_in2;
        default: alu_result = 0;
    endcase
end


// ================= EX/MEM =================
reg [31:0] EX_MEM_result, EX_MEM_B;
reg [4:0] EX_MEM_rd;
reg EX_MEM_reg_write, EX_MEM_mem_write, EX_MEM_mem_read, EX_MEM_mem_to_reg; // extensions of above stage values

always @(posedge clk1) begin
    EX_MEM_result <= alu_result;
    EX_MEM_B <= ID_EX_B;
    EX_MEM_rd <= ID_EX_rd;

    EX_MEM_reg_write <= ID_EX_reg_write;
    EX_MEM_mem_write <= ID_EX_mem_write;
    EX_MEM_mem_read  <= ID_EX_mem_read;
    EX_MEM_mem_to_reg <= ID_EX_mem_to_reg;
end


// ================= MEM =================
//reg [31:0] data_mem [0:255]; // data memory initialized at top
reg [31:0] mem_out; //to store the output of memeory before mux comes in play

// =================STORE=================
always @(posedge clk2) begin
    if (EX_MEM_mem_write) begin //when enable to write in register
        data_mem[EX_MEM_result[9:2]] <= EX_MEM_B; //here B input is writing in the register
        $display("MEM WRITE: addr=%d data=%d", EX_MEM_result[9:2], EX_MEM_B);//observing what value is written here
    end
end                                                                     //in store operatio only value is stored in memory

// ==================LOAD===================
always @(*) begin
    if (EX_MEM_mem_read) //enables to load from memeory
        mem_out = data_mem[EX_MEM_result[9:2]]; //here we are loading from aluout or data memeory based on control signal
    else                                        //EX_MEM_mem_read this decides which value to be stored
        mem_out = EX_MEM_result;
end


// ================= MEM/WB =================
reg [31:0] MEM_WB_result;
reg [31:0] MEM_WB_mem_out;   // registers for memeory WB interface
reg [4:0] MEM_WB_rd;
reg MEM_WB_reg_write;
reg MEM_WB_mem_to_reg;    

always @(posedge clk1) begin
     MEM_WB_mem_out <= mem_out;       //  memory output stored
    MEM_WB_result  <= EX_MEM_result; //  ALU result stored
    MEM_WB_rd <= EX_MEM_rd;
    MEM_WB_reg_write <= EX_MEM_reg_write;
    MEM_WB_mem_to_reg <= EX_MEM_mem_to_reg;
end


// ================= WB =================
wire [31:0] wb_data;  //data return in to gesister file

assign wb_data = (MEM_WB_mem_to_reg) ? MEM_WB_mem_out : MEM_WB_result; //based on the control signal MEM_WB_mem_to_reg
                                                                       
always @(posedge clk1) begin                                            //which value to be written in register
    if (MEM_WB_reg_write && MEM_WB_rd != 0)
        regs[MEM_WB_rd] <= wb_data;  //here data is stored at rd(destination register place)
end

endmodule

RISC_5_TEST.v
`timescale 1s/1s

module tb_pipeline_riscv;

reg clk1, clk2;

// Instantiate DUT
pipeline_riscv uut (
    .clk1(clk1),
    .clk2(clk2)
);

// ================= CLOCK GENERATION =================
initial begin
    clk1 = 0;
    clk2 = 0;
end

// Non-overlapping clocks
always #10 clk1 = ~clk1;

always begin
    #5 clk2 = 1;
    #5 clk2 = 0;
end

// ================= WAVEFORM =================
initial begin
    $dumpfile("pipeline_riscv.vcd");
    $dumpvars(0, tb_pipeline_riscv.uut);
end

// ================= MONITOR =================
initial begin
    $monitor("T=%0t PC=%0d INSTR=%h ALU=%0d x1=%0d x2=%0d x3=%0d",
        $time,
        uut.pc,
        uut.IF_ID_instr,
        uut.alu_result,
        uut.regs[1],
        uut.regs[2],
        uut.regs[3]
    );
end

// ================= TEST PROGRAM =================
initial begin

    // IMPORTANT: continuous indexing (0,1,2,3...)
    
    // ADDI x1, x0, 5
// ADDI x1, x0, 5
uut.instr_mem[0] = 32'b000000000101_00000_000_00001_0010011;

// ADDI x2, x0, 10
uut.instr_mem[1] = 32'b000000001010_00000_000_00010_0010011;

// NOP
uut.instr_mem[2] = 32'b000000000000_00000_000_00000_0010011;

// NOP
uut.instr_mem[3] = 32'b000000000000_00000_000_00000_0010011;

// ADD x3 = x1 + x2
uut.instr_mem[4] = 32'b0000000_00010_00001_000_00011_0110011;

// NOP
uut.instr_mem[5] = 32'b000000000000_00000_000_00000_0010011;

// NOP
uut.instr_mem[6] = 32'b000000000000_00000_000_00000_0010011;

// STORE x3 → MEM[0]
uut.instr_mem[7] = 32'b0000000_00011_00000_010_00000_0100011;

// NOP
uut.instr_mem[8] = 32'b000000000000_00000_000_00000_0010011;

// NOP
uut.instr_mem[9] = 32'b000000000000_00000_000_00000_0010011;

// LOAD x4 ← MEM[0]
uut.instr_mem[10] = 32'b000000000000_00000_010_00100_0000011;

// NOP
uut.instr_mem[11] = 32'b000000000000_00000_000_00000_0010011;

// NOP ⭐ (important)
uut.instr_mem[12] = 32'b000000000000_00000_000_00000_0010011;

// ADD x5 = x3 + x4
uut.instr_mem[13] = 32'b0000000_00100_00011_000_00101_0110011;

// ADD x5 = x3 + x4
uut.instr_mem[12] = 32'b0000000_00100_00011_000_00101_0110011;
    // Run simulation
    #500;

    // Final results
    $display("\n===== FINAL OUTPUT =====");
    $display("x1 = %0d", uut.regs[1]); // expect 5
    $display("x2 = %0d", uut.regs[2]); // expect 10
    $display("x3 = %0d", uut.regs[3]); // expect 15
    $display("x4 = %0d", uut.regs[4]); // expect 15
    $display("x5 = %0d", uut.regs[5]); // expect 30
    $display("MEM[0] = %0d", uut.data_mem[0]); // expect 15

    $finish;
end

endmodule

pipeline_riscv.vcd
$date
	Sat Apr 18 11:55:41 2026
$end
$version
	Icarus Verilog
$end
$timescale
	1s
$end
$scope module tb_pipeline_riscv $end
$scope module uut $end
$var wire 1 ! clk1 $end
$var wire 1 " clk2 $end
$var wire 32 # instruction [31:0] $end
$var wire 32 $ reg_data1 [31:0] $end
$var wire 32 % reg_data2 [31:0] $end
$var wire 32 & wb_data [31:0] $end
$var wire 5 ' rs2 [4:0] $end
$var wire 5 ( rs1 [4:0] $end
$var wire 5 ) rd [4:0] $end
$var wire 7 * opcode [6:0] $end
$var wire 32 + imm_s [31:0] $end
$var wire 32 , imm_i [31:0] $end
$var wire 32 - imm_b [31:0] $end
$var wire 7 . funct7 [6:0] $end
$var wire 3 / funct3 [2:0] $end
$var wire 32 0 alu_in2 [31:0] $end
$var reg 32 1 EX_MEM_B [31:0] $end
$var reg 1 2 EX_MEM_mem_read $end
$var reg 1 3 EX_MEM_mem_to_reg $end
$var reg 1 4 EX_MEM_mem_write $end
$var reg 5 5 EX_MEM_rd [4:0] $end
$var reg 1 6 EX_MEM_reg_write $end
$var reg 32 7 EX_MEM_result [31:0] $end
$var reg 32 8 ID_EX_A [31:0] $end
$var reg 32 9 ID_EX_B [31:0] $end
$var reg 3 : ID_EX_alu_ctrl [2:0] $end
$var reg 1 ; ID_EX_alu_src $end
$var reg 32 < ID_EX_imm [31:0] $end
$var reg 1 = ID_EX_mem_read $end
$var reg 1 > ID_EX_mem_to_reg $end
$var reg 1 ? ID_EX_mem_write $end
$var reg 5 @ ID_EX_rd [4:0] $end
$var reg 1 A ID_EX_reg_write $end
$var reg 32 B IF_ID_instr [31:0] $end
$var reg 32 C MEM_WB_mem_out [31:0] $end
$var reg 1 D MEM_WB_mem_to_reg $end
$var reg 5 E MEM_WB_rd [4:0] $end
$var reg 1 F MEM_WB_reg_write $end
$var reg 32 G MEM_WB_result [31:0] $end
$var reg 3 H alu_ctrl [2:0] $end
$var reg 32 I alu_result [31:0] $end
$var reg 1 J alu_src $end
$var reg 1 K branch $end
$var reg 32 L imm [31:0] $end
$var reg 32 M mem_out [31:0] $end
$var reg 1 N mem_read $end
$var reg 1 O mem_to_reg $end
$var reg 1 P mem_write $end
$var reg 32 Q pc [31:0] $end
$var reg 1 R reg_write $end
$var integer 32 S i [31:0] $end
$upscope $end
$upscope $end
$enddefinitions $end
#0
$dumpvars
b100000000 S
xR
b0 Q
xP
xO
xN
bx M
b0 L
xK
xJ
bx I
bx H
bx G
xF
bx E
xD
bx C
bx B
xA
bx @
x?
x>
x=
bx <
x;
bx :
bx 9
bx 8
bx 7
x6
bx 5
x4
x3
x2
bx 1
bx 0
bx /
bx .
bx0 -
bx ,
bx +
bx *
bx )
bx (
bx '
bx &
bx %
bx $
b10100000000000010010011 #
0"
0!
$end
#5
b0 <
1"
#10
b0 H
0O
0N
0P
0K
1J
1R
b101 L
b101000000000000100010011 #
b10011 *
b0 $
b0 (
b0 %
b101 '
b1 )
b0 /
b0 .
b101 ,
b1 +
b100000000000 -
b100 Q
b10100000000000010010011 B
0"
1!
#15
b101 I
b101 0
0>
0=
0?
1;
1A
b0 :
b1 @
b101 <
b0 9
b0 8
1"
#20
0"
0!
#25
1"
#30
b1010 L
b101 M
b1010 '
b10 )
b1010 ,
b10 +
b10 -
b10011 #
03
02
04
16
b1 5
b0 1
b101 7
b101000000000000100010011 B
b1000 Q
0"
1!
#35
b1010 I
b1010 0
b10 @
b1010 <
1"
#40
0"
0!
#45
1"
#50
b0 L
b0 '
b0 )
b0 ,
b0 +
b0 -
b1010 M
b101 &
b1100 Q
b10011 B
b10 5
b1010 7
0D
1F
b1 E
b101 G
b101 C
0"
1!
#55
b0 I
b0 0
b0 @
b0 <
1"
#60
0"
0!
#65
1"
#70
b1010 &
b0 M
b1000001000000110110011 #
b10 E
b1010 G
b1010 C
b0 5
b0 7
b10000 Q
0"
1!
#75
1"
#80
0"
0!
#85
1"
#90
0J
1R
b10011 #
b110011 *
b101 $
b1 (
b1010 %
b10 '
b11 )
b10 ,
b11 +
b100000000010 -
b0 &
b10100 Q
b1000001000000110110011 B
b0 E
b0 G
b0 C
0"
1!
#95
b1010 0
b1111 I
0;
b11 @
b1010 9
b101 8
1"
#100
0"
0!
#105
1"
#110
1J
1R
b1111 M
b10011 *
b0 $
b0 (
b0 %
b0 '
b0 )
b0 ,
b0 +
b0 -
b11 5
b1010 1
b1111 7
b10011 B
b11000 Q
0"
1!
#115
b0 0
b0 I
1;
b0 @
b0 9
b0 8
1"
#120
0"
0!
#125
1"
#130
b1100000010000000100011 #
b0 M
b1111 &
b11100 Q
b0 5
b0 1
b0 7
b11 E
b1111 G
b1111 C
0"
1!
#135
1"
#140
0"
0!
#145
1"
#150
1P
1J
0R
b0 &
b100011 *
b1111 %
b11 '
b10 /
b11 ,
b10011 #
b0 E
b0 G
b0 C
b1100000010000000100011 B
b100000 Q
0"
1!
#155
1?
0A
b1111 9
1"
#160
0"
0!
#165
1"
#170
1R
0P
1J
b10011 *
b0 %
b0 '
b0 /
b0 ,
b100100 Q
b10011 B
14
06
b1111 1
0"
1!
#175
0?
1A
b0 9
1"
#180
0"
0!
#185
1"
#190
b10001000000011 #
0F
04
16
b0 1
b101000 Q
0"
1!
#195
1"
#200
0"
0!
#205
1"
#210
1O
1N
1J
1R
b10011 #
b11 *
b100 )
b10 /
b100 +
b100 -
b101100 Q
b10001000000011 B
1F
0"
1!
#215
1>
1=
b100 @
1"
#220
0"
0!
#225
1"
#230
0O
0N
1J
1R
b1111 M
b10011 *
b0 )
b0 /
b0 +
b0 -
b10000011000001010110011 #
13
12
b100 5
b10011 B
b110000 Q
0"
1!
#235
0>
0=
b0 @
1"
#240
0"
0!
#245
1"
#250
0J
1R
b110011 *
b1111 $
b11 (
b100 '
b101 )
b100 ,
b101 +
b100000000100 -
b0 M
b1111 &
b110100 Q
b10000011000001010110011 B
03
02
b0 5
1D
b100 E
b1111 C
0"
1!
#255
b1111 I
0;
b101 @
b1111 8
1"
#260
0"
0!
#265
1"
#270
b0 &
b1111 M
bx #
b1111 %
0D
b0 E
b0 C
b101 5
b1111 7
b111000 Q
0"
1!
#275
b11110 I
b1111 0
b1111 9
1"
#280
0"
0!
#285
1"
#290
0R
bx *
bx $
bx (
bx %
bx '
bx )
bx /
bx .
bx ,
bx +
bx0 -
b11110 M
b1111 &
b111100 Q
bx B
b1111 1
b11110 7
b101 E
b1111 G
b1111 C
0"
1!
#295
bx 0
bx I
0A
bx @
bx 9
bx 8
1"
#300
0"
0!
#305
1"
#310
b11110 &
bx M
b11110 G
b11110 C
06
bx 5
bx 1
bx 7
b1000000 Q
0"
1!
#315
1"
#320
0"
0!
#325
1"
#330
bx &
b1000100 Q
0F
bx E
bx G
bx C
0"
1!
#335
1"
#340
0"
0!
#345
1"
#350
b1001000 Q
0"
1!
#355
1"
#360
0"
0!
#365
1"
#370
b1001100 Q
0"
1!
#375
1"
#380
0"
0!
#385
1"
#390
b1010000 Q
0"
1!
#395
1"
#400
0"
0!
#405
1"
#410
b1010100 Q
0"
1!
#415
1"
#420
0"
0!
#425
1"
#430
b1011000 Q
0"
1!
#435
1"
#440
0"
0!
#445
1"
#450
b1011100 Q
0"
1!
#455
1"
#460
0"
0!
#465
1"
#470
b1100000 Q
0"
1!
#475
1"
#480
0"
0!
#485
1"
#490
b1100100 Q
0"
1!
